CODING_FOObar_20220520.2-1.0.0.dist-info/DESCRIPTION.rst
CODING_FOObar_20220520.2-1.0.0.dist-info/METADATA
CODING_FOObar_20220520.2-1.0.0.dist-info/RECORD
CODING_FOObar_20220520.2-1.0.0.dist-info/WHEEL
CODING_FOObar_20220520.2-1.0.0.dist-info/metadata.json
CODING_FOObar_20220520.2-1.0.0.dist-info/top_level.txt
bar/speaker.py
