Metadata-Version: 2.0
Name: CODING-FOObar-20220520.2
Version: 1.0.0
Summary: requires python >= 3.7
Home-page: https://e.coding.net/codingcorp/coding-artifacts-demo.git
Author: coding
Author-email: coding@coding.com
License: MIT
Download-URL: https://codingcorp.coding.net/p/mayday/artifacts/297/pypi/package/471/version/5772
Keywords: PyPI,artifacts,Python
Platform: UNKNOWN
Requires-Python: >=3.8
License-File: LICENSE.txt
